supersafecalc/__init__.py
supersafecalc-2.0.0.dist-info/METADATA
supersafecalc-2.0.0.dist-info/WHEEL
supersafecalc-2.0.0.dist-info/top_level.txt
supersafecalc-2.0.0.dist-info/RECORD
