Metadata-Version: 2.4
Name: supersafecalc
Version: 2.0.0
Summary: Malicious supersafecalc package
Dynamic: summary
